{
  "layout": [
    [
      {
        "meta": {
          "showHeader": true,
          "showRefresh": false,
          "api": {
            "path": "/api/alert/{alertId}",
            "pathParams": {
              "alertId": ":pathParam"
            },
            "queryParams": {
              "date": "date:pathParam",
              "window": ""
            }
          },
          "title": "Alert Detail",
          "fetchDataFor": [
            {
              "id": "connection-status,connection-by-type,data-source-dest",
              "api": {
                "method": "POST",
                "path": "/api/analytics/reporting/executeById",
                "body": "data.rank_alert.chartsFilter$customParam",
                "pathParams": {},
                "queryParams": {
                  "window": ""
                },
                "loadOnce": true
              }
            },
            {
              "id": "timeline",
              "api": {
                "method": "GET",
                "path": "/api/alert/traffic",
                "pathParams": {},
                "queryParams": {
                  "count": 200,
                  "from": 0,
                  "window": "",
                  "filter": "data.rank_alert.trafficFilter$customParam",
                  "date": ":pathParam"
                }
              }
            }
          ]
        },
        "name": "AlertDetail",
        "attributes": {
          "style": {
            "backgroundColor": "#F7F7F9",
            "width": "250px",
            "flex": "0 0 250px"
          }
        },
        "id": "alert-detail",
        "type": "AlertDetailsNew"
      },
      {
        "meta": {
          "showHeader": true,
          "api": {
            "path": "/api/analytics/graph/{alertId}",
            "pathParams": {
              "alertId": ":pathParam"
            },
            "queryParams": {}
          },
          "title": "Overview"
        },
        "name": "NetworkGraph",
        "attributes": {
          "style": {
            "width": "100%"
          },
          "id": "NetworkGraph"
        },
        "id": "network-graph",
        "type": "NetworkGraph"
      }
    ],
    [
      {
        "id": "alert-activity",
        "type": "Compound",
        "name": "Compound",
        "meta": {
          "showHeader": true,
          "title": "Activity",
          "showRefresh": false
        },
        "innerStyle": {
          "flexDirection": "column"
        },
        "attributes": {
          "style": {
            "width": "300px",
            "flexDirection": "column"
          },
          "id": "activity"
        },
        "children": [
          {
            "chartOptions": {
              "xAxisName": "TIME",
              "divLineThickness": "2",
              "lineThickness": "1",
              "showYAxisValues": "1",
              "xAxisNameFontSize": "10",
              "yAxisNameFontSize": "10",
              "labelFontSize": "8",
              "drawAnchors": "1",
              "anchorRadius": "1",
              "showlegend": "0",
              "outCnvBaseFontSize": "8"
            },
            "chartData": {
              "multipleReports": true,
              "fieldMapping": {
                "x": [{
                  "reportId": "taf_conn_by_status",
                  "columns": ["date"]
                }],
                "y": [
                  {
                    "reportId": "taf_conn_by_status",
                    "columns": [
                      "count"
                    ],
                    "seriesname": "Connection Status"
                  }
                ]
              }
            },
            "meta": {
              "showHeader": true,
              "showRefresh": false,
              "api": null,
              "title": "Connection by Status"
            },
            "attributes": {
              "chartHeight": "200",
              "chartCaption": {
                "display": "none"
              },
              "style": {
                "width": "100%",
                "padding": 0,
                "boxShadow": "none",
                "marginBottom": "35px"
              },
              "header": {
                "style": {
                  "paddingBottom": 0
                },
                "title": {
                  "fontSize": "13px",
                  "fontWeight": 600,
                  "textTransform": "capitalize"
                }
              },
              "id": "connection-status-chart"
            },
            "id": "connection-status",
            "type": "MultiSeriesLineChart"
          },
          {
            "chartOptions": {
              "xAxisName": "TIME",
              "divLineThickness": "2",
              "lineThickness": "1",
              "showYAxisValues": "1",
              "xAxisNameFontSize": "10",
              "yAxisNameFontSize": "10",
              "labelFontSize": "8",
              "drawAnchors": "1",
              "anchorRadius": "1",
              "showlegend": "0",
              "outCnvBaseFontSize": "8"
            },
            "chartData": {
              "fieldMapping": {
                "x": [{
                  "reportId": "taf_conn_by_type",
                  "columns": ["date"]
                }],
                "y": [{
                  "reportId": "taf_conn_by_type",
                  "columns": ["count"]
                }]
              },
              "filter": {
                "reportId": "taf_conn_by_type",
                "columns": ["type"]
              }
            },
            "meta": {
              "showHeader": true,
              "showRefresh": false,
              "api": null,
              "title": "Connections by type"
            },
            "attributes": {
              "chartHeight": "200",
              "chartCaption": {
                "display": "none"
              },
              "style": {
                "width": "100%",
                "padding": 0,
                "boxShadow": "none",
                "marginBottom": "35px"
              },
              "header": {
                "style": {
                  "paddingBottom": 0
                },
                "title": {
                  "fontSize": "13px",
                  "fontWeight": 600,
                  "textTransform": "capitalize"
                }
              },
              "id": "connection-by-type-chart"
            },
            "id": "connection-by-type",
            "type": "MultiSeriesLineChart"
          },
          {
            "chartOptions": {
              "xAxisName": "TIME",
              "divLineThickness": "2",
              "lineThickness": "1",
              "showYAxisValues": "1",
              "xAxisNameFontSize": "10",
              "yAxisNameFontSize": "10",
              "labelFontSize": "8",
              "drawAnchors": "1",
              "anchorRadius": "1",
              "showlegend": "0",
              "outCnvBaseFontSize": "8"
            },
            "chartData": {
              "multipleReports": true,
              "fieldMapping": {
                "x": [{
                  "reportId": "taf_data_between_source_and_destination",
                  "columns": ["date"]
                }],
                "y": [
                  {
                    "reportId": "taf_data_between_source_and_destination",
                    "columns": [
                      "count"
                    ],
                    "seriesname": "Connection Status"
                  }
                ]
              }
            },
            "meta": {
              "showHeader": true,
              "showRefresh": false,
              "api": null,
              "title": "Data b/w source and destination"
            },
            "attributes": {
              "chartHeight": "200",
              "chartCaption": {
                "display": "none"
              },
              "style": {
                "width": "100%",
                "padding": 0,
                "boxShadow": "none"
              },
              "header": {
                "style": {
                  "paddingBottom": 0
                },
                "title": {
                  "fontSize": "13px",
                  "fontWeight": 600,
                  "textTransform": "capitalize"
                }
              },
              "id": "data-source-dest-chart"
            },
            "id": "data-source-dest",
            "type": "MultiSeriesLineChart"
          }
        ]
      }
    ]
  ]
}
